{"nodes": [{"id": "home_priya_documents_github_ai_aiinsight_tests_binary_validation_sh", "label": "binary-validation.sh", "file_type": "code", "source_file": "tests/binary-validation.sh", "source_location": "L1", "metadata": {"language": "bash", "kind": "file"}}, {"id": "home_priya_documents_github_ai_aiinsight_tests_binary_validation_sh__entry", "label": "binary-validation.sh script", "file_type": "code", "source_file": "tests/binary-validation.sh", "source_location": "L1", "metadata": {"language": "bash", "kind": "bash_entrypoint"}}, {"id": "tests_binary_validation_log", "label": "log()", "file_type": "code", "source_file": "tests/binary-validation.sh", "source_location": "L32", "metadata": {"language": "bash", "kind": "bash_function"}}, {"id": "tests_binary_validation_pass", "label": "pass()", "file_type": "code", "source_file": "tests/binary-validation.sh", "source_location": "L34", "metadata": {"language": "bash", "kind": "bash_function"}}, {"id": "tests_binary_validation_fail", "label": "fail()", "file_type": "code", "source_file": "tests/binary-validation.sh", "source_location": "L41", "metadata": {"language": "bash", "kind": "bash_function"}}, {"id": "tests_binary_validation_warn", "label": "warn()", "file_type": "code", "source_file": "tests/binary-validation.sh", "source_location": "L50", "metadata": {"language": "bash", "kind": "bash_function"}}, {"id": "tests_binary_validation_section", "label": "section()", "file_type": "code", "source_file": "tests/binary-validation.sh", "source_location": "L59", "metadata": {"language": "bash", "kind": "bash_function"}}, {"id": "tests_binary_validation_run_cmd", "label": "run_cmd()", "file_type": "code", "source_file": "tests/binary-validation.sh", "source_location": "L66", "metadata": {"language": "bash", "kind": "bash_function"}}, {"id": "tests_binary_validation_assert_exit", "label": "assert_exit()", "file_type": "code", "source_file": "tests/binary-validation.sh", "source_location": "L77", "metadata": {"language": "bash", "kind": "bash_function"}}, {"id": "tests_binary_validation_assert_output_contains", "label": "assert_output_contains()", "file_type": "code", "source_file": "tests/binary-validation.sh", "source_location": "L89", "metadata": {"language": "bash", "kind": "bash_function"}}, {"id": "tests_binary_validation_assert_file_exists", "label": "assert_file_exists()", "file_type": "code", "source_file": "tests/binary-validation.sh", "source_location": "L101", "metadata": {"language": "bash", "kind": "bash_function"}}, {"id": "tests_binary_validation_assert_dir_exists", "label": "assert_dir_exists()", "file_type": "code", "source_file": "tests/binary-validation.sh", "source_location": "L112", "metadata": {"language": "bash", "kind": "bash_function"}}, {"id": "tests_binary_validation_assert_not_empty", "label": "assert_not_empty()", "file_type": "code", "source_file": "tests/binary-validation.sh", "source_location": "L123", "metadata": {"language": "bash", "kind": "bash_function"}}, {"id": "tests_binary_validation_home", "label": "HOME", "file_type": "code", "source_file": "tests/binary-validation.sh", "source_location": "L174", "metadata": {"language": "bash", "kind": "code"}}, {"id": "tests_binary_validation_xdg_config_home", "label": "XDG_CONFIG_HOME", "file_type": "code", "source_file": "tests/binary-validation.sh", "source_location": "L175", "metadata": {"language": "bash", "kind": "code"}}, {"id": "tests_binary_validation_xdg_cache_home", "label": "XDG_CACHE_HOME", "file_type": "code", "source_file": "tests/binary-validation.sh", "source_location": "L176", "metadata": {"language": "bash", "kind": "code"}}], "edges": [{"source": "home_priya_documents_github_ai_aiinsight_tests_binary_validation_sh", "target": "home_priya_documents_github_ai_aiinsight_tests_binary_validation_sh__entry", "relation": "contains", "confidence": "EXTRACTED", "source_file": "tests/binary-validation.sh", "source_location": "L1", "weight": 1.0}, {"source": "home_priya_documents_github_ai_aiinsight_tests_binary_validation_sh", "target": "tests_binary_validation_log", "relation": "defines", "confidence": "EXTRACTED", "source_file": "tests/binary-validation.sh", "source_location": "L32", "weight": 1.0}, {"source": "home_priya_documents_github_ai_aiinsight_tests_binary_validation_sh", "target": "tests_binary_validation_pass", "relation": "defines", "confidence": "EXTRACTED", "source_file": "tests/binary-validation.sh", "source_location": "L34", "weight": 1.0}, {"source": "home_priya_documents_github_ai_aiinsight_tests_binary_validation_sh", "target": "tests_binary_validation_fail", "relation": "defines", "confidence": "EXTRACTED", "source_file": "tests/binary-validation.sh", "source_location": "L41", "weight": 1.0}, {"source": "home_priya_documents_github_ai_aiinsight_tests_binary_validation_sh", "target": "tests_binary_validation_warn", "relation": "defines", "confidence": "EXTRACTED", "source_file": "tests/binary-validation.sh", "source_location": "L50", "weight": 1.0}, {"source": "home_priya_documents_github_ai_aiinsight_tests_binary_validation_sh", "target": "tests_binary_validation_section", "relation": "defines", "confidence": "EXTRACTED", "source_file": "tests/binary-validation.sh", "source_location": "L59", "weight": 1.0}, {"source": "home_priya_documents_github_ai_aiinsight_tests_binary_validation_sh", "target": "tests_binary_validation_run_cmd", "relation": "defines", "confidence": "EXTRACTED", "source_file": "tests/binary-validation.sh", "source_location": "L66", "weight": 1.0}, {"source": "home_priya_documents_github_ai_aiinsight_tests_binary_validation_sh", "target": "tests_binary_validation_assert_exit", "relation": "defines", "confidence": "EXTRACTED", "source_file": "tests/binary-validation.sh", "source_location": "L77", "weight": 1.0}, {"source": "home_priya_documents_github_ai_aiinsight_tests_binary_validation_sh", "target": "tests_binary_validation_assert_output_contains", "relation": "defines", "confidence": "EXTRACTED", "source_file": "tests/binary-validation.sh", "source_location": "L89", "weight": 1.0}, {"source": "home_priya_documents_github_ai_aiinsight_tests_binary_validation_sh", "target": "tests_binary_validation_assert_file_exists", "relation": "defines", "confidence": "EXTRACTED", "source_file": "tests/binary-validation.sh", "source_location": "L101", "weight": 1.0}, {"source": "home_priya_documents_github_ai_aiinsight_tests_binary_validation_sh", "target": "tests_binary_validation_assert_dir_exists", "relation": "defines", "confidence": "EXTRACTED", "source_file": "tests/binary-validation.sh", "source_location": "L112", "weight": 1.0}, {"source": "home_priya_documents_github_ai_aiinsight_tests_binary_validation_sh", "target": "tests_binary_validation_assert_not_empty", "relation": "defines", "confidence": "EXTRACTED", "source_file": "tests/binary-validation.sh", "source_location": "L123", "weight": 1.0}, {"source": "home_priya_documents_github_ai_aiinsight_tests_binary_validation_sh", "target": "tests_binary_validation_home", "relation": "defines", "confidence": "EXTRACTED", "source_file": "tests/binary-validation.sh", "source_location": "L174", "weight": 1.0}, {"source": "home_priya_documents_github_ai_aiinsight_tests_binary_validation_sh", "target": "tests_binary_validation_xdg_config_home", "relation": "defines", "confidence": "EXTRACTED", "source_file": "tests/binary-validation.sh", "source_location": "L175", "weight": 1.0}, {"source": "home_priya_documents_github_ai_aiinsight_tests_binary_validation_sh", "target": "tests_binary_validation_xdg_cache_home", "relation": "defines", "confidence": "EXTRACTED", "source_file": "tests/binary-validation.sh", "source_location": "L176", "weight": 1.0}, {"source": "home_priya_documents_github_ai_aiinsight_tests_binary_validation_sh", "target": "tests_binary_validation_home", "relation": "defines", "confidence": "EXTRACTED", "source_file": "tests/binary-validation.sh", "source_location": "L661", "weight": 1.0}, {"source": "home_priya_documents_github_ai_aiinsight_tests_binary_validation_sh__entry", "target": "tests_binary_validation_section", "relation": "calls", "confidence": "EXTRACTED", "source_file": "tests/binary-validation.sh", "source_location": "L140", "weight": 1.0, "context": "call"}, {"source": "home_priya_documents_github_ai_aiinsight_tests_binary_validation_sh__entry", "target": "tests_binary_validation_pass", "relation": "calls", "confidence": "EXTRACTED", "source_file": "tests/binary-validation.sh", "source_location": "L183", "weight": 1.0, "context": "call"}, {"source": "home_priya_documents_github_ai_aiinsight_tests_binary_validation_sh__entry", "target": "tests_binary_validation_fail", "relation": "calls", "confidence": "EXTRACTED", "source_file": "tests/binary-validation.sh", "source_location": "L196", "weight": 1.0, "context": "call"}, {"source": "home_priya_documents_github_ai_aiinsight_tests_binary_validation_sh__entry", "target": "tests_binary_validation_warn", "relation": "calls", "confidence": "EXTRACTED", "source_file": "tests/binary-validation.sh", "source_location": "L233", "weight": 1.0, "context": "call"}, {"source": "tests_binary_validation_pass", "target": "tests_binary_validation_log", "relation": "calls", "confidence": "EXTRACTED", "source_file": "tests/binary-validation.sh", "source_location": "L38", "weight": 1.0, "context": "call"}, {"source": "tests_binary_validation_fail", "target": "tests_binary_validation_log", "relation": "calls", "confidence": "EXTRACTED", "source_file": "tests/binary-validation.sh", "source_location": "L47", "weight": 1.0, "context": "call"}, {"source": "tests_binary_validation_warn", "target": "tests_binary_validation_log", "relation": "calls", "confidence": "EXTRACTED", "source_file": "tests/binary-validation.sh", "source_location": "L56", "weight": 1.0, "context": "call"}, {"source": "tests_binary_validation_section", "target": "tests_binary_validation_log", "relation": "calls", "confidence": "EXTRACTED", "source_file": "tests/binary-validation.sh", "source_location": "L63", "weight": 1.0, "context": "call"}, {"source": "tests_binary_validation_run_cmd", "target": "tests_binary_validation_log", "relation": "calls", "confidence": "EXTRACTED", "source_file": "tests/binary-validation.sh", "source_location": "L73", "weight": 1.0, "context": "call"}, {"source": "tests_binary_validation_assert_exit", "target": "tests_binary_validation_fail", "relation": "calls", "confidence": "EXTRACTED", "source_file": "tests/binary-validation.sh", "source_location": "L84", "weight": 1.0, "context": "call"}, {"source": "tests_binary_validation_assert_output_contains", "target": "tests_binary_validation_fail", "relation": "calls", "confidence": "EXTRACTED", "source_file": "tests/binary-validation.sh", "source_location": "L96", "weight": 1.0, "context": "call"}, {"source": "tests_binary_validation_assert_file_exists", "target": "tests_binary_validation_fail", "relation": "calls", "confidence": "EXTRACTED", "source_file": "tests/binary-validation.sh", "source_location": "L107", "weight": 1.0, "context": "call"}, {"source": "tests_binary_validation_assert_dir_exists", "target": "tests_binary_validation_fail", "relation": "calls", "confidence": "EXTRACTED", "source_file": "tests/binary-validation.sh", "source_location": "L118", "weight": 1.0, "context": "call"}, {"source": "tests_binary_validation_assert_not_empty", "target": "tests_binary_validation_fail", "relation": "calls", "confidence": "EXTRACTED", "source_file": "tests/binary-validation.sh", "source_location": "L129", "weight": 1.0, "context": "call"}]}